weavenn/__init__.py
weavenn/ann.py
weavenn/weavenn.py
weavenn-0.0.3.dist-info/METADATA
weavenn-0.0.3.dist-info/WHEEL
weavenn-0.0.3.dist-info/top_level.txt
weavenn-0.0.3.dist-info/RECORD
