Metadata-Version: 2.1
Name: weavenn
Version: 0.0.3
Summary: Density-aware k-nearest neighbor graph from cloud points
Home-page: https://github.com/kerighan/weavenn
Author: Maixent Chenebaux
Author-email: max.chbx@gmail.com
License: UNKNOWN
Platform: UNKNOWN
Classifier: License :: OSI Approved :: MIT License
Classifier: Operating System :: OS Independent
Requires-Dist: networkx
Requires-Dist: numpy
Requires-Dist: scikit-learn
Requires-Dist: louvaincpp
